Metadata-Version: 2.4
Name: tubeupac
Version: 0.0.38
Summary: altCensored fork of tubeup, a VOD service to Archive.org uploader
License: GNU GENERAL PUBLIC LICENSE
Project-URL: Homepage, https://github.com/altCensored/tubeupac
Project-URL: Bug Tracker, https://github.com/altCensored/tubeupac/issues
Requires-Python: >=3.8
License-File: LICENSE
Requires-Dist: internetarchive
Requires-Dist: docopt==0.6.2
Requires-Dist: yt-dlp
Dynamic: license-file
